resume_importer/Upload_result.py
resume_importer/Upload_supervisor.py
resume_importer/Upload_worker.py
resume_importer/resume_importer.py
riminder_resume_importer-0.0.4.dist-info/METADATA
riminder_resume_importer-0.0.4.dist-info/WHEEL
riminder_resume_importer-0.0.4.dist-info/entry_points.txt
riminder_resume_importer-0.0.4.dist-info/top_level.txt
riminder_resume_importer-0.0.4.dist-info/RECORD
