Metadata-Version: 2.1
Name: riminder-resume-importer
Version: 0.0.4
Summary: Riminder resume importer.
Home-page: https://github.com/Riminder/riminder-resumes-importer
Author: riminder
Author-email: contact@rimider.net
License: MIT
Platform: UNKNOWN
Requires-Python: >=3.5
Requires-Dist: riminder
